dartrig/__init__.py
dartrig/annotations.py
dartrig/parser/__init__.py
dartrig/parser/parse_common.py
dartrig/parser/parser_dsaf.py
dartrig/parser/parser_search.py
dartrig-0.2.1.dist-info/LICENSE
dartrig-0.2.1.dist-info/METADATA
dartrig-0.2.1.dist-info/WHEEL
dartrig-0.2.1.dist-info/top_level.txt
dartrig-0.2.1.dist-info/RECORD
