Metadata-Version: 2.1
Name: dartrig
Version: 0.2.1
Summary: dartrig api wrapper
Home-page: https://github.com/cheddars/dart_rigger
Author: cheddars
Author-email: nezahrish@gmail.com
License: MIT
Classifier: Programming Language :: Python :: 3.8
Classifier: License :: OSI Approved :: MIT License
Classifier: Operating System :: OS Independent
License-File: LICENSE
Requires-Dist: requests
Requires-Dist: bs4
Requires-Dist: adt-cache (==0.0.14)
Requires-Dist: crawler-commons (==0.0.54)
